congress/__init__.py
congress/bills.py
congress/client.py
congress/committees.py
congress/members.py
congress/nominations.py
congress/utils.py
congress/votes.py
python_congress-0.3.5.dist-info/DESCRIPTION.rst
python_congress-0.3.5.dist-info/METADATA
python_congress-0.3.5.dist-info/RECORD
python_congress-0.3.5.dist-info/WHEEL
python_congress-0.3.5.dist-info/metadata.json
python_congress-0.3.5.dist-info/top_level.txt
